easy_load_ssh-1.1.dist-info/METADATA
easy_load_ssh-1.1.dist-info/RECORD
easy_load_ssh-1.1.dist-info/WHEEL
easy_load_ssh-1.1.dist-info/entry_points.txt
easy_load_ssh-1.1.dist-info/top_level.txt
elssh/__init__.py
elssh/elssh.py
