Metadata-Version: 2.1
Name: easy-load-ssh
Version: 1.1
Summary: UNKNOWN
Home-page: UNKNOWN
Author: John Frederick Cornish IV
Author-email: johncornishthe4th@gmail.com
License: GPLv3
Platform: UNKNOWN
Requires-Dist: click
Requires-Dist: PyYAML
